python_ishare/__init__.py
python_ishare/authentication.py
python_ishare/clients.py
python_ishare/exceptions.py
python_ishare/verification.py
python_ishare-0.0.3.dist-info/LICENSE
python_ishare-0.0.3.dist-info/METADATA
python_ishare-0.0.3.dist-info/WHEEL
python_ishare-0.0.3.dist-info/RECORD
