Metadata-Version: 2.1
Name: python_ishare
Version: 0.0.3
Summary: iShare python interface client package
Requires-Python: >=3.8.1,<4.0.0
Classifier: Programming Language :: Python :: 3
Classifier: Programming Language :: Python :: 3.9
Classifier: Programming Language :: Python :: 3.10
Classifier: Programming Language :: Python :: 3.11
Classifier: Programming Language :: Python :: 3.12
Requires-Dist: cryptography (>=41.0.5,<42.0.0)
Requires-Dist: pyjwt (>=2.8.0,<3.0.0)
